<?xml version="1.0" encoding="UTF-8"?>
<group>
	<suggestion id="3001" advisorId="2001" title="CardTitle_1" description="CardDescription_1">
		<suggestionOptions>
			<suggestionOption id="1" text="Card_OptA_1" money="-20" capacity="1000" />
			<suggestionOption id="2" text="Card_OptB_1" money="-40" capacity="2000" />
		</suggestionOptions>
		<requirements>
			<gamePhaseRequirement>
				<phaseId>1</phaseId>
			</gamePhaseRequirement>
		</requirements>
	</suggestion>
	<suggestion id="3002" advisorId="2002" title="CardTitle_2" description="CardDescription_2">
		<suggestionOptions>
			<suggestionOption id="1" text="Card_OptA_2" money="30000" growthRate="4" />
			<suggestionOption id="2" text="Card_OptB_2" money="-50"/>
		</suggestionOptions>
		<requirements>
			<gamePhaseRequirement>
				<phaseId>1</phaseId>
				<phaseId>2</phaseId>
			</gamePhaseRequirement>
		</requirements>
	</suggestion>
	<suggestion id="3003" advisorId="2003" title="CardTitle_3" description="CardDescription_3">
		<suggestionOptions>
			<suggestionOption id="1" text="Card_OptA_3" money="20000" growthRate="-3" startStoryId="4001" />
			<suggestionOption id="2" text="Card_OptB_3" publicOpinion="-10" growthRate="3" />
		</suggestionOptions>
		<requirements>
			<gamePhaseRequirement>
				<phaseId>2</phaseId>
				<phaseId>3</phaseId>
			</gamePhaseRequirement>
		</requirements>
	</suggestion>
	<suggestion id="3004" advisorId="2004" title="CardTitle_4" description="CardDescription_4">
		<suggestionOptions>
			<suggestionOption id="1" text="Card_OptA_4" money="-200" vaccine="20" />
			<suggestionOption id="2" text="Card_OptB_4" publicOpinion="10" growthRate="-2" />
		</suggestionOptions>
		<requirements>
			<gamePhaseRequirement>
				<phaseId>3</phaseId>
			</gamePhaseRequirement>
			<gameStoryRequirement>
				<storyId>4001</storyId>
			</gameStoryRequirement>
		</requirements>
	</suggestion>
	<suggestion id="3005" advisorId="2005" title="CardTitle_5" description="CardDescription_5" >
		<suggestionOptions>
			<suggestionOption id="1" text="Card_OptA_" money="10000" vaccine="8" stopStoryId="4001" />
			<suggestionOption id="2" text="Card_OptB_5" publicOpinion="-5" growthRate="6" />
		</suggestionOptions>
		<requirements>
			<gamePhaseRequirement>
				<phaseId>3</phaseId>
			</gamePhaseRequirement>
			<gameStoryRequirement>
				<storyId>4001</storyId>
			</gameStoryRequirement>
		</requirements>
	</suggestion>
</group>